MANIFEST.in
setup.py
terraai_preprocessing/__init__.py
terraai_preprocessing.egg-info/PKG-INFO
terraai_preprocessing.egg-info/SOURCES.txt
terraai_preprocessing.egg-info/dependency_links.txt
terraai_preprocessing.egg-info/not-zip-safe
terraai_preprocessing.egg-info/top_level.txt
terraai_preprocessing/combinatorics/API_helpers_comb.py
terraai_preprocessing/combinatorics/API_main_comb.py
terraai_preprocessing/combinatorics/__init__.py
terraai_preprocessing/preprocessing/__init__.py
terraai_preprocessing/preprocessing/config.json
terraai_preprocessing/preprocessing/pp_helpers.py
terraai_preprocessing/preprocessing/pp_main.py