Metadata-Version: 1.0
Name: terraai-preprocessing
Version: 0.2
Summary: TerraAI preprocessing module
Home-page: UNKNOWN
Author: aamir
Author-email: aamir@terra.ai
License: TerraAI
Platform: UNKNOWN
